livekit/plugins/openai/__init__.py
livekit/plugins/openai/embeddings.py
livekit/plugins/openai/llm.py
livekit/plugins/openai/log.py
livekit/plugins/openai/models.py
livekit/plugins/openai/py.typed
livekit/plugins/openai/stt.py
livekit/plugins/openai/tts.py
livekit/plugins/openai/utils.py
livekit/plugins/openai/version.py
aeon_plugins_openai-0.6.0.dist-info/METADATA
aeon_plugins_openai-0.6.0.dist-info/WHEEL
aeon_plugins_openai-0.6.0.dist-info/top_level.txt
aeon_plugins_openai-0.6.0.dist-info/RECORD
