Metadata-Version: 2.1
Name: aeon-plugins-openai
Version: 0.6.0
Summary: Agent Framework plugin for services from OpenAI
Home-page: https://github.com/livekit/agents
License: Apache-2.0
Project-URL: Documentation, https://docs.livekit.io
Project-URL: Website, https://livekit.io/
Project-URL: Source, https://github.com/livekit/agents
Keywords: webrtc,realtime,audio,video,livekit
Classifier: Intended Audience :: Developers
Classifier: License :: OSI Approved :: Apache Software License
Classifier: Topic :: Multimedia :: Sound/Audio
Classifier: Topic :: Multimedia :: Video
Classifier: Topic :: Scientific/Engineering :: Artificial Intelligence
Classifier: Programming Language :: Python :: 3
Classifier: Programming Language :: Python :: 3.9
Classifier: Programming Language :: Python :: 3.10
Classifier: Programming Language :: Python :: 3 :: Only
Requires-Python: >=3.9.0
Requires-Dist: livekit-agents[codecs,images] >=0.7.2
Requires-Dist: openai ~=1.35
